{
  "subject_code": "CH101",
  "title": "Sample Question Paper 2",
  "type": "end_sem",
  "year": "2025-26",
  "metadata": {
    "difficulty": "medium",
    "modules_covered": [
      "Module 1",
      "Module 2",
      "Module 3",
      "Module 4"
    ]
  },
  "questions": {
    "A1": {
      "group": "A",
      "number": "A1",
      "text": "The time-independent Schrödinger wave equation in operator form is:",
      "marks": 1,
      "co": "CO1",
      "bl": "L1",
      "is_preview": true,
      "options": [
        {
          "key": "a",
          "text": "$\\hat{H}\\psi = E\\psi$"
        },
        {
          "key": "b",
          "text": "$\\hat{H}\\psi = mc^2\\psi$"
        },
        {
          "key": "c",
          "text": "$E = h\\nu$"
        },
        {
          "key": "d",
          "text": "$\\lambda = h/p$"
        }
      ]
    },
    "A2": {
      "group": "A",
      "number": "A2",
      "text": "Which quantum number determines the shape of an orbital?",
      "marks": 1,
      "co": "CO1",
      "bl": "L1",
      "options": [
        {
          "key": "a",
          "text": "Principal quantum number ($n$)"
        },
        {
          "key": "b",
          "text": "Azimuthal quantum number ($l$)"
        },
        {
          "key": "c",
          "text": "Magnetic quantum number ($m_l$)"
        },
        {
          "key": "d",
          "text": "Spin quantum number ($m_s$)"
        }
      ]
    },
    "A3": {
      "group": "A",
      "number": "A3",
      "text": "Electronegativity of elements in the periodic table generally:",
      "marks": 1,
      "co": "CO1",
      "bl": "L2",
      "options": [
        {
          "key": "a",
          "text": "Increases across a period and increases down a group"
        },
        {
          "key": "b",
          "text": "Decreases across a period and increases down a group"
        },
        {
          "key": "c",
          "text": "Increases across a period and decreases down a group"
        },
        {
          "key": "d",
          "text": "Decreases across a period and decreases down a group"
        }
      ]
    },
    "A4": {
      "group": "A",
      "number": "A4",
      "text": "Silicon doped with phosphorus produces:",
      "marks": 1,
      "co": "CO5",
      "bl": "L2",
      "options": [
        {
          "key": "a",
          "text": "p-type semiconductor"
        },
        {
          "key": "b",
          "text": "n-type semiconductor"
        },
        {
          "key": "c",
          "text": "Intrinsic semiconductor"
        },
        {
          "key": "d",
          "text": "Metallic conductor"
        }
      ]
    },
    "A5": {
      "group": "A",
      "number": "A5",
      "text": "Entropy of the universe for a spontaneous process is:",
      "marks": 1,
      "co": "CO2",
      "bl": "L1",
      "options": [
        {
          "key": "a",
          "text": "$\\Delta S_{\\text{universe}} < 0$"
        },
        {
          "key": "b",
          "text": "$\\Delta S_{\\text{universe}} = 0$"
        },
        {
          "key": "c",
          "text": "$\\Delta S_{\\text{universe}} > 0$"
        },
        {
          "key": "d",
          "text": "$\\Delta S_{\\text{universe}} = -1$"
        }
      ]
    },
    "A6": {
      "group": "A",
      "number": "A6",
      "text": "The standard EMF of a Daniell cell is approximately:",
      "marks": 1,
      "co": "CO2",
      "bl": "L1",
      "options": [
        {
          "key": "a",
          "text": "0.34 V"
        },
        {
          "key": "b",
          "text": "0.76 V"
        },
        {
          "key": "c",
          "text": "1.10 V"
        },
        {
          "key": "d",
          "text": "2.00 V"
        }
      ]
    },
    "A7": {
      "group": "A",
      "number": "A7",
      "text": "Nylon 6,6 is prepared by the condensation of hexamethylenediamine with:",
      "marks": 1,
      "co": "CO1",
      "bl": "L1",
      "options": [
        {
          "key": "a",
          "text": "Terephthalic acid"
        },
        {
          "key": "b",
          "text": "Adipic acid"
        },
        {
          "key": "c",
          "text": "Acetic acid"
        },
        {
          "key": "d",
          "text": "Formaldehyde"
        }
      ]
    },
    "A8": {
      "group": "A",
      "number": "A8",
      "text": "HDPE stands for:",
      "marks": 1,
      "co": "CO1",
      "bl": "L1",
      "options": [
        {
          "key": "a",
          "text": "Heavy Duty Polyethylene"
        },
        {
          "key": "b",
          "text": "High Density Polyethylene"
        },
        {
          "key": "c",
          "text": "Highly Durable Polyester"
        },
        {
          "key": "d",
          "text": "Hydrated Diethyl Polyethylene"
        }
      ]
    },
    "A9": {
      "group": "A",
      "number": "A9",
      "text": "Cetane number is a measure of quality of:",
      "marks": 1,
      "co": "CO4",
      "bl": "L1",
      "options": [
        {
          "key": "a",
          "text": "Petrol"
        },
        {
          "key": "b",
          "text": "Diesel"
        },
        {
          "key": "c",
          "text": "LPG"
        },
        {
          "key": "d",
          "text": "CNG"
        }
      ]
    },
    "A10": {
      "group": "A",
      "number": "A10",
      "text": "According to Markovnikov's rule, the addition of HBr to propene gives:",
      "marks": 1,
      "co": "CO3",
      "bl": "L2",
      "options": [
        {
          "key": "a",
          "text": "1-bromopropane"
        },
        {
          "key": "b",
          "text": "2-bromopropane"
        },
        {
          "key": "c",
          "text": "3-bromopropane"
        },
        {
          "key": "d",
          "text": "1,2-dibromopropane"
        }
      ]
    },
    "A11": {
      "group": "A",
      "number": "A11",
      "text": "The fingerprint region in IR spectroscopy lies in the range:",
      "marks": 1,
      "co": "CO3",
      "bl": "L1",
      "options": [
        {
          "key": "a",
          "text": "$4000\\text{–}1500$ cm⁻¹"
        },
        {
          "key": "b",
          "text": "$1500\\text{–}400$ cm⁻¹"
        },
        {
          "key": "c",
          "text": "$400\\text{–}100$ cm⁻¹"
        },
        {
          "key": "d",
          "text": "$100\\text{–}10$ cm⁻¹"
        }
      ]
    },
    "A12": {
      "group": "A",
      "number": "A12",
      "text": "Which type of corrosion occurs when two dissimilar metals are in contact in the presence of an electrolyte?",
      "marks": 1,
      "co": "CO4",
      "bl": "L2",
      "options": [
        {
          "key": "a",
          "text": "Pitting corrosion"
        },
        {
          "key": "b",
          "text": "Galvanic corrosion"
        },
        {
          "key": "c",
          "text": "Crevice corrosion"
        },
        {
          "key": "d",
          "text": "Stress corrosion"
        }
      ]
    },
    "B1": {
      "group": "B",
      "number": "B1",
      "text": "State de Broglie's hypothesis and calculate the de Broglie wavelength of an electron moving with a velocity of $1.0 \\times 10^6$ m/s. (Mass of electron = $9.1 \\times 10^{-31}$ kg, $h = 6.626 \\times 10^{-34}$ J·s)",
      "marks": 4,
      "co": "CO1",
      "bl": "L3",
      "is_preview": true
    },
    "B2": {
      "group": "B",
      "number": "B2",
      "text": "Define Gibbs free energy. Calculate $\\Delta G^\\circ$ for the combustion of methane at 298 K, given $\\Delta H^\\circ = -890.4$ kJ/mol and $\\Delta S^\\circ = -242.2$ J/mol·K. Is the reaction spontaneous?",
      "marks": 4,
      "co": "CO2",
      "bl": "L3"
    },
    "B3": {
      "group": "B",
      "number": "B3",
      "text": "Write the synthesis and applications of HDPE and LDPE. What is tacticity in polymers?",
      "marks": 4,
      "co": "CO1",
      "bl": "L2"
    },
    "B4": {
      "group": "B",
      "number": "B4",
      "text": "Compare chemical corrosion and electrochemical corrosion. Define calorific value, HCV, and LCV.",
      "marks": 4,
      "co": "CO4",
      "bl": "L2"
    },
    "B5": {
      "group": "B",
      "number": "B5",
      "text": "Compare $S_N1$ and $S_N2$ nucleophilic substitution reactions with examples.",
      "marks": 4,
      "co": "CO3",
      "bl": "L2"
    },
    "B6": {
      "group": "B",
      "number": "B6",
      "text": "Explain the working principle and applications of Lithium-ion batteries.",
      "marks": 4,
      "co": "CO2",
      "bl": "L2"
    },
    "C1": {
      "group": "C",
      "number": "C1",
      "text": "(a) Write the time-independent Schrödinger wave equation and explain its significance. [3]\n(b) State Slater's rule and calculate the effective nuclear charge on the valence electron of Sodium ($Z = 11$). [4]\n(c) Explain the variation of electron affinity and electronegativity across a period and down a group. [3]",
      "marks": 10,
      "co": "CO1",
      "bl": "L2",
      "is_preview": true
    },
    "C2": {
      "group": "C",
      "number": "C2",
      "text": "(a) State and explain the second law of thermodynamics. [2]\n(b) Define entropy and derive the general expression for entropy change of an ideal gas. Explain its physical significance. [5]\n(c) Using standard enthalpies of formation, calculate the standard enthalpy of combustion of methane. Given: $\\Delta H^\\circ_f[\\text{H}_2\\text{O}(l)] = -285.83$ kJ/mol, $\\Delta H^\\circ_f[\\text{CO}_2(g)] = -393.51$ kJ/mol, $\\Delta H^\\circ_f[\\text{CH}_4(g)] = -74.87$ kJ/mol. [3]",
      "marks": 10,
      "co": "CO2",
      "bl": "L3"
    },
    "C3": {
      "group": "C",
      "number": "C3",
      "text": "(a) Explain intrinsic and extrinsic semiconductors with examples. [3]\n(b) Describe n-type and p-type semiconductors. How is conductivity improved by doping? [4]\n(c) Discuss the role of Silicon and Germanium as semiconductor-based memory materials. [3]",
      "marks": 10,
      "co": "CO5",
      "bl": "L2"
    },
    "C4": {
      "group": "C",
      "number": "C4",
      "text": "(a) Explain electrophilic addition reactions with the mechanism of addition of HBr to propene. [3]\n(b) State Markovnikov's rule and the peroxide effect with examples. [3]\n(c) Write the synthesis and uses of Paracetamol and Aspirin. [4]",
      "marks": 10,
      "co": "CO3",
      "bl": "L3"
    },
    "C5": {
      "group": "C",
      "number": "C5",
      "text": "(a) Explain the applications of UV-Visible spectroscopy. [3]\n(b) State Lambert-Beer's law. Explain how $\\lambda_{\\max}$ and the concentration of an unknown solution can be determined. [4]\n(c) What is the fingerprint region in IR spectroscopy? Explain its significance. [3]",
      "marks": 10,
      "co": "CO3",
      "bl": "L2"
    }
  },
  "answers": {
    "A1": {
      "question_number": "A1",
      "correct_option": "a",
      "solution": "The time-independent Schrödinger wave equation in operator form is:\n\n$$\\hat{H}\\psi = E\\psi$$\n\nwhere $\\hat{H}$ = Hamiltonian operator (total energy: kinetic + potential), $\\psi$ = wave function, $E$ = total energy.\n\nIn full form: $-\\frac{\\hbar^2}{2m}\\nabla^2\\psi + V\\psi = E\\psi$\n\nOther options: (b) incorrect, (c) Planck's equation, (d) de Broglie equation.",
      "key_points": [
        "Schrödinger equation: $\\hat{H}\\psi = E\\psi$",
        "$\\hat{H}$ = Hamiltonian, $\\psi$ = wave function",
        "Fundamental equation of quantum mechanics"
      ]
    },
    "A2": {
      "question_number": "A2",
      "correct_option": "b",
      "solution": "The **azimuthal quantum number ($l$)** determines the **shape** of an orbital.\n\n| $l$ | Orbital | Shape |\n|-----|---------|-------|\n| 0 | s | Spherical |\n| 1 | p | Dumbbell |\n| 2 | d | Double dumbbell / cloverleaf |\n| 3 | f | Complex |\n\nOther quantum numbers: $n$ (size), $m_l$ (orientation), $m_s$ (spin direction).",
      "key_points": [
        "Azimuthal quantum number ($l$) determines shape",
        "$l = 0$ (s), $l = 1$ (p), $l = 2$ (d), $l = 3$ (f)"
      ]
    },
    "A3": {
      "question_number": "A3",
      "correct_option": "c",
      "solution": "Electronegativity trends:\n- **Across a period** (left → right): **Increases** — nuclear charge increases, atomic size decreases\n- **Down a group** (top → bottom): **Decreases** — atomic size increases, shielding increases\n\nFluorine has the highest electronegativity (3.98, Pauling scale).",
      "key_points": [
        "EN increases across a period, decreases down a group",
        "Fluorine has the highest electronegativity"
      ]
    },
    "A4": {
      "question_number": "A4",
      "correct_option": "b",
      "solution": "Phosphorus (Group 15, 5 valence electrons) replaces Si (4 valence electrons) → one **extra free electron** → **n-type semiconductor**.\n\n- Phosphorus is a **donor impurity**\n- Electrons are majority carriers\n- Group 13 elements (B, Al, Ga) produce p-type instead.",
      "key_points": [
        "Phosphorus (Group 15) → n-type semiconductor",
        "Extra electron = donor impurity",
        "Electrons are majority carriers"
      ]
    },
    "A5": {
      "question_number": "A5",
      "correct_option": "c",
      "solution": "For a **spontaneous process**, total entropy of the universe always **increases**:\n\n$$\\Delta S_{\\text{universe}} = \\Delta S_{\\text{system}} + \\Delta S_{\\text{surroundings}} > 0$$\n\n- $> 0$: spontaneous\n- $= 0$: reversible (equilibrium)\n- $< 0$: non-spontaneous",
      "key_points": [
        "$\\Delta S_{\\text{universe}} > 0$ for spontaneous",
        "Second law of thermodynamics",
        "$= 0$ at equilibrium"
      ]
    },
    "A6": {
      "question_number": "A6",
      "correct_option": "c",
      "solution": "The **Daniell cell** (Zn anode, Cu cathode):\n\n$$E^\\circ_{\\text{cell}} = E^\\circ_{\\text{Cu}^{2+}/\\text{Cu}} - E^\\circ_{\\text{Zn}^{2+}/\\text{Zn}} = (+0.34) - (-0.76) = 1.10 \\text{ V}$$",
      "key_points": [
        "Daniell cell: Zn|Zn²⁺||Cu²⁺|Cu",
        "$E^\\circ = 1.10$ V"
      ]
    },
    "A7": {
      "question_number": "A7",
      "correct_option": "b",
      "solution": "**Nylon 6,6** = condensation of hexamethylenediamine + **adipic acid** (hexanedioic acid).\n\n\"6,6\" = 6 carbons in each monomer. Water is eliminated as a by-product.",
      "key_points": [
        "Nylon 6,6 = hexamethylenediamine + adipic acid",
        "Condensation polymerization, water eliminated",
        "6,6 = 6 carbons in each monomer"
      ]
    },
    "A8": {
      "question_number": "A8",
      "correct_option": "b",
      "solution": "**HDPE = High Density Polyethylene**\n\n- Linear chains with minimal branching → close packing → density 0.94–0.97 g/cm³\n- More crystalline, rigid, and stronger than LDPE\n- Applications: Bottles, pipes, containers",
      "key_points": [
        "HDPE = High Density Polyethylene",
        "Linear chains, less branching, higher density",
        "Used for bottles, pipes, containers"
      ]
    },
    "A9": {
      "question_number": "A9",
      "correct_option": "b",
      "solution": "**Cetane number** measures ignition quality of **diesel**.\n\n- % of cetane (n-hexadecane) in a reference mixture matching diesel's ignition\n- Higher cetane = shorter ignition delay = better diesel\n- **Octane number** is for petrol.",
      "key_points": [
        "Cetane number = diesel quality",
        "Higher cetane = shorter ignition delay",
        "Octane number is for petrol"
      ]
    },
    "A10": {
      "question_number": "A10",
      "correct_option": "b",
      "solution": "**Markovnikov's rule:** In HX addition to unsymmetrical alkenes, H goes to the carbon with **more H atoms**, halide to the **more substituted** carbon.\n\nPropene + HBr → **2-bromopropane** ($\\text{CH}_3\\text{CHBrCH}_3$)\n\nThe 2° carbocation intermediate is more stable than 1°.",
      "key_points": [
        "Markovnikov: H to C with more H's, halide to more substituted C",
        "HBr + propene → 2-bromopropane",
        "More substituted carbocation is more stable"
      ]
    },
    "A11": {
      "question_number": "A11",
      "correct_option": "b",
      "solution": "The **fingerprint region**: **1500–400 cm⁻¹**\n\n- Complex bending vibrations and C–C, C–O, C–N stretching\n- Unique for each compound — used for identification\n- Region above 1500 cm⁻¹ is the functional group region",
      "key_points": [
        "Fingerprint region: 1500–400 cm⁻¹",
        "Unique for each compound",
        "Used for identification by comparison"
      ]
    },
    "A12": {
      "question_number": "A12",
      "correct_option": "b",
      "solution": "**Galvanic corrosion** occurs when **two dissimilar metals** are in electrical contact with an **electrolyte**.\n\n- More active (anodic) metal corrodes preferentially\n- More noble (cathodic) metal is protected\n- Driven by potential difference in galvanic series",
      "key_points": [
        "Galvanic: two dissimilar metals + electrolyte",
        "More active metal corrodes faster",
        "Potential difference drives corrosion"
      ]
    },
    "B1": {
      "question_number": "B1",
      "solution": "**de Broglie's Hypothesis:** Every moving particle has **wave-like properties**. The wavelength is:\n\n$$\\lambda = \\frac{h}{mv} = \\frac{h}{p}$$\n\nwhere $h$ = Planck's constant, $m$ = mass, $v$ = velocity, $p$ = momentum.\n\nThis wave nature is significant for microscopic particles but negligible for macroscopic objects.\n\n**Calculation:**\n\nGiven: $m = 9.1 \\times 10^{-31}$ kg, $v = 1.0 \\times 10^{6}$ m/s, $h = 6.626 \\times 10^{-34}$ J·s\n\n$$\\lambda = \\frac{6.626 \\times 10^{-34}}{9.1 \\times 10^{-31} \\times 1.0 \\times 10^{6}} = \\frac{6.626 \\times 10^{-34}}{9.1 \\times 10^{-25}}$$\n\n$$\\lambda = 7.28 \\times 10^{-10} \\text{ m} = 7.28 \\text{ Å}$$\n\n**Result: $\\lambda \\approx 7.28$ Å** — comparable to atomic dimensions, confirming electron wave nature.",
      "key_points": [
        "de Broglie: $\\lambda = h/mv$",
        "Wave nature significant for microscopic particles",
        "$\\lambda \\approx 7.28$ Å for the given electron"
      ]
    },
    "B2": {
      "question_number": "B2",
      "solution": "**Gibbs free energy ($G$)** measures the maximum **non-expansion work** obtainable from a system at constant $T$ and $P$:\n\n$$G = H - TS \\quad \\Rightarrow \\quad \\Delta G = \\Delta H - T\\Delta S$$\n\n**Calculation:**\n\nGiven: $\\Delta H^\\circ = -890.4$ kJ/mol, $\\Delta S^\\circ = -242.2$ J/mol·K = $-0.2422$ kJ/mol·K, $T = 298$ K\n\n$$\\Delta G^\\circ = -890.4 - (298 \\times (-0.2422))$$\n\n$$\\Delta G^\\circ = -890.4 + 72.18 = -818.22 \\text{ kJ/mol}$$\n\nSince $\\Delta G^\\circ < 0$, the combustion of methane is **spontaneous** at 298 K.\n\n**Result: $\\Delta G^\\circ = -818.22$ kJ/mol (spontaneous)**",
      "key_points": [
        "$\\Delta G = \\Delta H - T\\Delta S$",
        "$\\Delta G^\\circ = -818.22$ kJ/mol",
        "$\\Delta G < 0$ → spontaneous reaction"
      ]
    },
    "B3": {
      "question_number": "B3",
      "solution": "**HDPE (High Density Polyethylene):**\n\n*Synthesis:* Ethylene polymerized using **Ziegler-Natta catalyst** ($\\text{TiCl}_4 + \\text{Al(C}_2\\text{H}_5)_3$) at low pressure (6–7 atm), 60–70°C.\n\n- Linear chains, minimal branching → density 0.94–0.97 g/cm³\n- *Applications:* Water pipes, bottles, containers, crates, fuel tanks\n\n**LDPE (Low Density Polyethylene):**\n\n*Synthesis:* Free radical polymerization at **high pressure** (1000–2000 atm), 150–300°C with peroxide initiators.\n\n- Highly branched → density 0.91–0.94 g/cm³, more flexible\n- *Applications:* Plastic bags, cling wrap, squeeze bottles, cable insulation\n\n**Tacticity** refers to the relative **stereochemical arrangement** of substituent groups on the polymer backbone. Three types:\n\n1. **Isotactic:** All substituents on the **same side** (crystalline, high melting point)\n2. **Syndiotactic:** Substituents **alternate** on opposite sides\n3. **Atactic:** **Random** arrangement (amorphous, soft)",
      "key_points": [
        "HDPE: Ziegler-Natta, linear, dense; LDPE: high-pressure, branched, flexible",
        "Tacticity: isotactic (same side), syndiotactic (alternating), atactic (random)"
      ]
    },
    "B4": {
      "question_number": "B4",
      "solution": "**Chemical vs. Electrochemical Corrosion:**\n\n| Feature | Chemical | Electrochemical |\n|---------|---------|------------------|\n| Mechanism | Direct chemical attack | Galvanic cell formation |\n| Medium | Dry gases / anhydrous liquids | Aqueous electrolyte |\n| Also called | Dry corrosion | Wet corrosion |\n| Electrolyte | Not required | Required (moisture) |\n| Current flow | No | Yes (anode to cathode) |\n| Example | Tarnishing of silver by H₂S | Rusting of iron in moist air |\n\n**Fuel Definitions:**\n\n**Calorific Value:** Total heat energy released by complete combustion of a unit mass of fuel. (kJ/kg)\n\n**HCV (Higher/Gross Calorific Value):** Heat when fuel burns and **water vapour condenses** to liquid. Includes latent heat of condensation.\n\n**LCV (Lower/Net Calorific Value):** Heat when **water remains as vapour**. Excludes latent heat.\n\n$$\\text{LCV} = \\text{HCV} - \\frac{9H}{100} \\times L$$\n\nwhere $H$ = % hydrogen, $L$ = latent heat of steam. LCV < HCV always.",
      "key_points": [
        "Chemical: dry, direct; Electrochemical: wet, galvanic cells",
        "HCV includes latent heat; LCV does not",
        "LCV < HCV always"
      ]
    },
    "B5": {
      "question_number": "B5",
      "solution": "| Feature | $S_N1$ | $S_N2$ |\n|---------|--------|--------|\n| Full form | Substitution Nucleophilic Unimolecular | Substitution Nucleophilic Bimolecular |\n| Mechanism | Two steps (via carbocation) | One step (concerted, backside attack) |\n| Rate law | Rate $= k[\\text{substrate}]$ | Rate $= k[\\text{substrate}][\\text{nucleophile}]$ |\n| Rate depends on | Only substrate | Both substrate and nucleophile |\n| Substrate preference | $3^\\circ > 2^\\circ > 1^\\circ$ | $1^\\circ > 2^\\circ > 3^\\circ$ |\n| Stereochemistry | Racemization | Walden inversion |\n| Example | $(\\text{CH}_3)_3\\text{CBr} + \\text{OH}^-$ | $\\text{CH}_3\\text{Br} + \\text{OH}^-$ |\n\n**Key difference:** $S_N1$ proceeds through a **carbocation intermediate** (2 steps), so it favours $3^\\circ$ substrates (more stable carbocation). $S_N2$ is a **concerted single step** with backside nucleophilic attack, so it favours $1^\\circ$ substrates (less steric hindrance).",
      "key_points": [
        "$S_N1$: unimolecular, carbocation, racemization, favours 3°",
        "$S_N2$: bimolecular, concerted, inversion, favours 1°",
        "Rate law differs: $S_N1$ depends only on substrate"
      ]
    },
    "B6": {
      "question_number": "B6",
      "solution": "**Lithium-ion batteries** are rechargeable cells working on **intercalation** of Li⁺ ions.\n\n**Components:**\n- **Anode:** Graphite ($\\text{LiC}_6$)\n- **Cathode:** $\\text{LiCoO}_2$ (or $\\text{LiFePO}_4$, $\\text{LiMnO}_2$)\n- **Electrolyte:** $\\text{LiPF}_6$ in organic solvent\n- **Separator:** Porous membrane\n\n**During discharging:**\n- Anode: $\\text{LiC}_6 \\rightarrow \\text{Li}^+ + e^- + \\text{C}_6$ (oxidation)\n- Cathode: $\\text{Li}^+ + e^- + \\text{CoO}_2 \\rightarrow \\text{LiCoO}_2$ (reduction)\n- Li⁺ moves anode → cathode through electrolyte; electrons through external circuit\n\n**During charging:** Reverse process with external power.\n\n**Applications:** Mobile phones, laptops, electric vehicles, solar energy storage, medical devices, power tools.",
      "key_points": [
        "Works by intercalation of Li⁺ between electrodes",
        "Discharge: Li⁺ anode → cathode",
        "Applications: phones, EVs, energy storage"
      ]
    },
    "C1": {
      "question_number": "C1",
      "solution": "**(a) Schrödinger Wave Equation:**\n\n$$-\\frac{\\hbar^2}{2m}\\nabla^2\\psi + V\\psi = E\\psi \\quad \\text{or} \\quad \\hat{H}\\psi = E\\psi$$\n\nwhere $\\hbar = h/2\\pi$, $m$ = particle mass, $\\nabla^2$ = Laplacian operator, $V$ = potential energy, $E$ = total energy, $\\psi$ = wave function.\n\n**Significance:**\n- $\\psi$ has no direct physical meaning, but $|\\psi|^2$ gives the **probability density** of finding the particle\n- Solving it gives allowed **energy levels** and **wave functions** (orbitals)\n- Replaces classical orbits with **probability distributions**\n- Fundamental equation governing quantum mechanical behaviour of matter\n\n**(b) Slater's Rule:**\n\n$$Z_{\\text{eff}} = Z - \\sigma$$\n\n**Rules for $\\sigma$:**\n1. Group electrons: $(1s)(2s, 2p)(3s, 3p)(3d)(4s, 4p)...$\n2. Electrons to the right → **0**\n3. Same group → **0.35** each (1s: **0.30**)\n4. For s, p: $(n-1)$ → **0.85**; $(n-2)$ and inner → **1.00**\n5. For d, f: all inner groups → **1.00**\n\n**Na ($Z = 11$), valence 3s electron:**\n\nConfig: $(1s^2)(2s^2 2p^6)(3s^1)$\n\n- Same group (3s): 0 others × 0.35 = **0**\n- $(n-1)$ (2s, 2p): 8 × 0.85 = **6.80**\n- $(n-2)$ (1s): 2 × 1.00 = **2.00**\n\n$\\sigma = 0 + 6.80 + 2.00 = 8.80$\n\n$$Z_{\\text{eff}} = 11 - 8.80 = 2.20$$\n\n**Result: $Z_{\\text{eff}} = 2.20$** — low effective charge explains Na's easy electron loss.\n\n**(c) Electron Affinity and Electronegativity Trends:**\n\n**Electron Affinity (EA):**\n\n*Across a period:* EA generally **increases** — smaller size, higher $Z_{\\text{eff}}$, atoms accept electrons more readily. Exceptions: Group 2 (filled s) and Group 15 (half-filled p) have lower EA.\n\nChlorine has the highest EA (not fluorine — F's tiny size causes electron repulsion).\n\n*Down a group:* EA generally **decreases** — larger size, incoming electron farther from nucleus. Exception: F < Cl.\n\n**Electronegativity (EN):**\n\n*Across a period:* EN **increases** — smaller size, higher $Z_{\\text{eff}}$, stronger pull on bonding electrons.\n\n*Down a group:* EN **decreases** — larger size, greater shielding.\n\nFluorine is the most electronegative element (EN = 3.98, Pauling scale).",
      "key_points": [
        "Schrödinger: $\\hat{H}\\psi = E\\psi$; $|\\psi|^2$ = probability density",
        "$Z_{\\text{eff}} = 2.20$ for Na valence electron",
        "EA and EN increase across period, decrease down group"
      ]
    },
    "C2": {
      "question_number": "C2",
      "solution": "**(a) Second Law of Thermodynamics:**\n\n- **Kelvin-Planck:** No heat engine can convert all absorbed heat completely into work (100% efficiency impossible).\n- **Clausius:** Heat cannot flow spontaneously from a colder to a hotter body.\n- **Entropy:** $\\Delta S_{\\text{universe}} \\geq 0$ for all real processes.\n\nThe second law defines the **direction** of natural processes — they proceed to increase universal entropy.\n\n**(b) Entropy — Definition, Derivation, Significance:**\n\n**Entropy ($S$)** measures the **degree of disorder/randomness** of a system.\n\nFor a reversible process: $dS = \\delta q_{\\text{rev}}/T$\n\n**General expression for ideal gas** (change from $T_1, V_1$ to $T_2, V_2$):\n\nFrom first law: $\\delta q_{\\text{rev}} = dU + PdV = nC_V dT + \\frac{nRT}{V}dV$\n\n$$\\Delta S = \\int \\frac{\\delta q_{\\text{rev}}}{T} = \\int_{T_1}^{T_2} \\frac{nC_V}{T}dT + \\int_{V_1}^{V_2} \\frac{nR}{V}dV$$\n\n$$\\boxed{\\Delta S = nC_V \\ln\\frac{T_2}{T_1} + nR\\ln\\frac{V_2}{V_1}}$$\n\n**Physical significance:**\n1. Measures **unavailable energy** — energy that cannot be converted to work\n2. Related to microstates: $S = k_B \\ln W$ (Boltzmann)\n3. Nature tends towards **maximum entropy** (2nd law)\n4. At absolute zero: $S = 0$ for a perfect crystal (3rd law)\n\n**(c) Enthalpy of Combustion:**\n\n$\\text{CH}_4(g) + 2\\text{O}_2(g) \\rightarrow \\text{CO}_2(g) + 2\\text{H}_2\\text{O}(l)$\n\n$$\\Delta H^\\circ_{\\text{comb}} = \\sum \\Delta H^\\circ_f(\\text{products}) - \\sum \\Delta H^\\circ_f(\\text{reactants})$$\n\n$$= [(-393.51) + 2(-285.83)] - [(-74.87) + 0]$$\n\n$$= [-393.51 - 571.66] - [-74.87] = -965.17 + 74.87$$\n\n$$\\boxed{\\Delta H^\\circ_{\\text{comb}} = -890.30 \\text{ kJ/mol}}$$",
      "key_points": [
        "Second law: entropy of universe always increases",
        "$\\Delta S = nC_V \\ln(T_2/T_1) + nR \\ln(V_2/V_1)$",
        "$\\Delta H^\\circ_{\\text{combustion}} = -890.30$ kJ/mol for methane"
      ]
    },
    "C3": {
      "question_number": "C3",
      "solution": "**(a) Intrinsic and Extrinsic Semiconductors:**\n\n**Intrinsic:** Pure semiconductors, conductivity from **thermal excitation** only. $n_e = n_h$. Very low conductivity at room temperature.\n- Examples: Pure Si (band gap 1.12 eV), pure Ge (0.67 eV)\n\n**Extrinsic:** Doped with impurities → much higher conductivity. Either electrons or holes are majority carriers.\n- Examples: Si doped with P (n-type), Si doped with B (p-type)\n\n**(b) n-type and p-type Semiconductors:**\n\n**n-type:**\n- Doped with **Group 15** (pentavalent): P, As, Sb\n- 5th valence electron is free → **donor impurity**\n- **Electrons** = majority carriers, holes = minority\n- Fermi level shifts toward conduction band\n\n**p-type:**\n- Doped with **Group 13** (trivalent): B, Al, Ga\n- Creates a **hole** (vacancy) → **acceptor impurity**\n- **Holes** = majority carriers, electrons = minority\n- Fermi level shifts toward valence band\n\n**How doping improves conductivity:** Intrinsic conductivity depends only on thermally generated pairs (very limited). Even tiny amounts of dopant (1 in $10^6$ atoms) introduce additional carriers, increasing conductivity by **several orders of magnitude**.\n\n**(c) Silicon and Germanium as Memory Materials:**\n\n**Silicon:**\n- Band gap 1.12 eV — optimal for room-temperature operation\n- Basis of **MOSFET transistors** in SRAM, DRAM, Flash memory\n- $\\text{SiO}_2$ forms a natural, high-quality insulating layer (crucial for gate oxide)\n- Abundant and cheap to process\n\n**Germanium:**\n- Band gap 0.67 eV — first semiconductor used in transistors historically\n- Higher **electron and hole mobility** than Si → faster switching\n- **SiGe alloys** combine Si's manufacturing advantage with Ge's speed\n- Used in high-performance cache memory and radiation-hardened aerospace applications",
      "key_points": [
        "Intrinsic: pure, low conductivity; Extrinsic: doped, much higher",
        "n-type: Group 15 (donor, electrons); p-type: Group 13 (acceptor, holes)",
        "Si: MOSFET basis, 1.12 eV; Ge: higher mobility, SiGe alloys"
      ]
    },
    "C4": {
      "question_number": "C4",
      "solution": "**(a) Electrophilic Addition — HBr to Propene:**\n\n**Electrophilic addition:** An electrophile attacks the $\\pi$-bond of an alkene, breaking it and forming new $\\sigma$-bonds.\n\n**Mechanism:**\n\n**Step 1 — Protonation (slow):** $\\pi$-electrons attack $\\text{H}^+$ from HBr:\n$$\\text{CH}_3\\text{CH=CH}_2 + \\text{H}^+ \\rightarrow \\text{CH}_3\\text{CH}^+\\text{CH}_3$$\nH adds to terminal C → more stable **2° carbocation** forms.\n\n**Step 2 — Nucleophilic attack (fast):** $\\text{Br}^-$ attacks the carbocation:\n$$\\text{CH}_3\\text{CH}^+\\text{CH}_3 + \\text{Br}^- \\rightarrow \\text{CH}_3\\text{CHBrCH}_3$$\n\n**Product:** 2-bromopropane (Markovnikov product).\n\n**(b) Markovnikov's Rule and Peroxide Effect:**\n\n**Markovnikov's Rule:** In HX addition to unsymmetrical alkenes, H adds to the carbon with **more hydrogens** (less substituted), halide to the **more substituted** carbon.\n\n*Example:* Propene + HBr → **2-bromopropane** (H to $\\text{CH}_2$, Br to $\\text{CH}$)\n\n**Peroxide Effect (Anti-Markovnikov / Kharasch Effect):**\n\nWith **organic peroxides**, HBr adds in the **opposite** manner via free radical mechanism:\n\n*Example:* Propene + HBr $\\xrightarrow{\\text{peroxide}}$ **1-bromopropane** (Br to terminal C)\n\n**Important:** Only works with **HBr** — not HCl (C–Cl too strong) or HI (H–I too weak).\n\n**(c) Synthesis of Paracetamol and Aspirin:**\n\n**Paracetamol (Acetaminophen):**\n\n*Synthesis:* Acetylation of **p-aminophenol** with **acetic anhydride**:\n$$\\text{p-aminophenol} + (\\text{CH}_3\\text{CO})_2\\text{O} \\rightarrow \\text{Paracetamol} + \\text{CH}_3\\text{COOH}$$\n\nThe $-\\text{NH}_2$ group reacts to form an amide bond ($-\\text{NHCOCH}_3$).\n\n*Uses:* Antipyretic (reduces fever), analgesic (pain relief — headache, body pain), safer for stomach than aspirin.\n\n**Aspirin (Acetylsalicylic acid):**\n\n*Synthesis:* Acetylation of **salicylic acid** with **acetic anhydride** (conc. $\\text{H}_2\\text{SO}_4$ catalyst):\n$$\\text{Salicylic acid} + (\\text{CH}_3\\text{CO})_2\\text{O} \\xrightarrow{\\text{H}_2\\text{SO}_4} \\text{Aspirin} + \\text{CH}_3\\text{COOH}$$\n\nThe phenolic $-\\text{OH}$ forms an ester bond ($-\\text{OCOCH}_3$).\n\n*Uses:* Analgesic (pain), antipyretic (fever), anti-inflammatory (NSAID), antiplatelet (low-dose prevents blood clots → heart attack/stroke prevention).",
      "key_points": [
        "Electrophilic addition via carbocation intermediate",
        "Markovnikov: halide to more substituted C; Peroxide reverses (HBr only)",
        "Paracetamol: p-aminophenol + acetic anhydride; Aspirin: salicylic acid + acetic anhydride"
      ]
    },
    "C5": {
      "question_number": "C5",
      "solution": "**(a) Applications of UV-Visible Spectroscopy:**\n\n1. **Identification of compounds:** Characteristic $\\lambda_{\\max}$ values identify functional groups and conjugation\n2. **Quantitative analysis:** Beer-Lambert law determines unknown concentrations from absorbance\n3. **Purity determination:** Impurities with different absorption can be detected\n4. **Study of conjugation:** Increased conjugation → red shift (bathochromic shift) of $\\lambda_{\\max}$\n5. **Reaction kinetics:** Absorbance changes over time track reaction progress\n6. **Pharmaceutical analysis:** Drug quality control and assay\n\n**(b) Lambert-Beer's Law:**\n\n**Statement:** Absorbance of a solution is directly proportional to **concentration** and **path length** of the absorbing medium:\n\n$$A = \\varepsilon \\cdot c \\cdot l$$\n\nwhere $A$ = absorbance, $\\varepsilon$ = molar absorptivity (L mol⁻¹ cm⁻¹), $c$ = concentration (mol/L), $l$ = path length (cm).\n\nAlso: $A = \\log(I_0/I)$\n\n**Determination of $\\lambda_{\\max}$:**\n1. Prepare a solution at known concentration\n2. Measure absorbance at different wavelengths across UV-Vis range\n3. Plot **absorbance vs. wavelength** → absorption spectrum\n4. Wavelength of **maximum absorbance** = $\\lambda_{\\max}$\n\n**Determination of unknown concentration:**\n1. Prepare standard solutions of known concentrations\n2. Measure absorbance of each at $\\lambda_{\\max}$\n3. Plot **absorbance vs. concentration** → **calibration curve** (straight line)\n4. Measure absorbance of unknown at the same $\\lambda_{\\max}$\n5. Read concentration from the calibration curve\n6. Or use: $c = A/(\\varepsilon \\cdot l)$ if $\\varepsilon$ is known\n\n**(c) Fingerprint Region in IR Spectroscopy:**\n\nThe fingerprint region: **1500–400 cm⁻¹**.\n\n**Characteristics:**\n- Contains complex **bending vibrations**, C–C/C–O/C–N stretching, and skeletal vibrations\n- **Unique for every compound** — no two different molecules have the same pattern\n\n**Significance:**\n1. **Compound identification:** Matching unknown spectrum with reference database confirms identity\n2. **Distinguishing isomers:** Structural isomers with similar functional groups differ in fingerprint region\n3. **Quality control:** Verifies identity and purity in pharmaceutical/industrial settings\n4. **Authentication:** Confirms if a sample matches the claimed substance\n\nThe region above 1500 cm⁻¹ (4000–1500 cm⁻¹) is the **functional group region** with characteristic peaks: O–H (~3300 cm⁻¹), C=O (~1700 cm⁻¹), N–H (~3400 cm⁻¹).",
      "key_points": [
        "UV-Vis: quantitative analysis, purity check, kinetics",
        "Beer-Lambert: $A = \\varepsilon cl$; calibration curve for unknown concentration",
        "Fingerprint region: 1500–400 cm⁻¹, unique for each compound"
      ]
    }
  }
}