{
  "code": "CH101",
  "name": "Engineering Chemistry",
  "short_name": "Engg. Chemistry",
  "regulation": "R25",
  "semester": 1,
  "department": "IT",
  "college": "JISCE",
  "exam_pattern": {
    "total_marks": 60,
    "duration_minutes": 180,
    "groups": [
      {
        "name": "A",
        "label": "Group A",
        "instructions": "Answer any 10 out of 12 questions",
        "questions_count": 12,
        "attempt_count": 10,
        "marks_per_question": 1,
        "question_type": "mcq"
      },
      {
        "name": "B",
        "label": "Group B",
        "instructions": "Answer any 5 out of 6 questions",
        "questions_count": 6,
        "attempt_count": 5,
        "marks_per_question": 4,
        "question_type": "short"
      },
      {
        "name": "C",
        "label": "Group C",
        "instructions": "Answer any 3 out of 5 questions",
        "questions_count": 5,
        "attempt_count": 3,
        "marks_per_question": 10,
        "question_type": "long"
      }
    ]
  }
}